nanoSQLite/__init__.py
nanoSQLite/nanoSQLite.py
tests/__init__.py
tests/test_database.py
nanoSQLite-1.1.4.dist-info/LICENSE
nanoSQLite-1.1.4.dist-info/METADATA
nanoSQLite-1.1.4.dist-info/WHEEL
nanoSQLite-1.1.4.dist-info/top_level.txt
nanoSQLite-1.1.4.dist-info/RECORD
