Metadata-Version: 2.1
Name: nanoSQLite
Version: 1.1.4
Summary: A lightweight wrapper for the SQLite3 Python module.
Home-page: https://github.com/stefanluth/nanoSQLite
Author: Stefan Luthardt
License: MIT
License-File: LICENSE
